aibuilder/__init__.py
aibuilder/common/__init__.py
aibuilder/common/constants.py
aibuilder/common/graph_client.py
aibuilder/common/utils.py
aibuilder/common/auth/__init__.py
aibuilder/common/auth/constants.py
aibuilder/common/auth/d365_connector.py
aibuilder/common/auth/exceptions.py
aibuilder/common/auth/token_cache_manager.py
aibuilder/common/paconnector/__init__.py
aibuilder/common/paconnector/constants.py
aibuilder/common/paconnector/exceptions.py
aibuilder/common/paconnector/powerapps_connector.py
aibuilder/common/paconnector/request_builder.py
aibuilder/common/paconnector/connector/__init__.py
aibuilder/common/paconnector/connector/connector_request_builder.py
aibuilder/common/paconnector/connector/create_custom_connector.py
aibuilder/common/paconnector/connector/exceptions.py
aibuilder/common/paconnector/connector/powerapps_custom_connector.py
aibuilder/common/paconnector/connector/resource_provider.py
aibuilder/core/__init__.py
aibuilder/core/constants.py
aibuilder/core/environment.py
aibuilder/core/model_connection.py
aibuilder/models/__init__.py
aibuilder/models/aib_binding.py
aibuilder/models/aib_model_client.py
aibuilder/models/constants.py
aibuilder/models/exceptions.py
aibuilder/models/model_client_response.py
aibuilder/models/model_management_client.py
aibuilder/models/open_api_specification.py
aibuilder/models/helpers/__init__.py
aibuilder/models/helpers/ai_model.py
aibuilder/models/helpers/constants.py
aibuilder/models/helpers/data_model_operator.py
aibuilder/models/helpers/data_specification.py
aibuilder/models/helpers/exceptions.py
aibuilder/models/helpers/run_configuration.py
aibuilder/models/helpers/train_configuration.py
aibuilder/models/helpers/utils.py
tests/common/__init__.py
tests/common/test_graph_client.py
tests/common/test_utils.py
tests/common/paconnector/__init__.py
tests/common/paconnector/conftest.py
tests/common/paconnector/test_powerapps_connector.py
tests/common/paconnector/test_request_builder.py
aibuilder-0.0.54.dist-info/License
aibuilder-0.0.54.dist-info/METADATA
aibuilder-0.0.54.dist-info/WHEEL
aibuilder-0.0.54.dist-info/top_level.txt
aibuilder-0.0.54.dist-info/RECORD
