Metadata-Version: 2.1
Name: aibuilder
Version: 0.0.54
Summary: Python SDK to register ML model with AI Builder
Home-page: UNKNOWN
Author: Microsoft Corporation
License: MIT
Keywords: azure,powerapps,connectors,aibuilder,connection
Platform: UNKNOWN
Requires-Python: >=3.8,<3.11
Requires-Dist: pytest (==6.1.2)
Requires-Dist: msal (==1.15.0)
Requires-Dist: requests (==2.25.0)
Requires-Dist: prance (==0.18.2)
Requires-Dist: openapi-spec-validator (==0.3.0)
Requires-Dist: PyJWT (==2.4.0)
Requires-Dist: azureml-sdk (==1.38.0)
Requires-Dist: polling2 (==0.4.7)
